muon_fsdp2.py
muon_fsdp2-0.3.0.dist-info/licenses/LICENSE
muon_fsdp2-0.3.0.dist-info/METADATA
muon_fsdp2-0.3.0.dist-info/WHEEL
muon_fsdp2-0.3.0.dist-info/top_level.txt
muon_fsdp2-0.3.0.dist-info/RECORD
