Metadata-Version: 2.4
Name: muon-fsdp2
Version: 0.3.0
Summary: Muon FSDP2 is a implementation of Muon optimizer for FSDP2
Author-email: Sami Jaghouar <sami.jaghouar@gmail.com>
License:                                  Apache License
Project-URL: Homepage, https://github.com/samsja/muon_fsdp_2
Project-URL: Repository, https://github.com/samsja/muon_fsdp_2
Project-URL: Documentation, https://github.com/samsja/muon_fsdp_2#muon-fsdp2-package
Project-URL: Issues, https://github.com/samsja/muon_fsdp_2/issues
Keywords: muon,optimizer,fsdp2,pytorch,deep-learning
Classifier: Development Status :: 3 - Alpha
Classifier: Intended Audience :: Developers
Classifier: Intended Audience :: Science/Research
Classifier: Programming Language :: Python :: 3
Classifier: Programming Language :: Python :: 3.10
Classifier: Programming Language :: Python :: 3.11
Classifier: Programming Language :: Python :: 3.12
Classifier: Topic :: Scientific/Engineering :: Artificial Intelligence
Requires-Python: >=3.10
License-File: LICENSE
Requires-Dist: torch
Dynamic: license-file
